scrunner/__init__.py
scrunner/arguments.py
scrunner/config.py
scrunner/html.py
scrunner/runner.py
scrunner/scripts.py
scrunner/version.py
scrunner-0.1.2.data/scripts/scrun
scrunner-0.1.2.dist-info/LICENSE
scrunner-0.1.2.dist-info/METADATA
scrunner-0.1.2.dist-info/WHEEL
scrunner-0.1.2.dist-info/top_level.txt
scrunner-0.1.2.dist-info/RECORD
