Metadata-Version: 2.1
Name: scrunner
Version: 0.1.2
Summary: Runs scripts with associated metadata and puts together a summary page.
Home-page: https://github.com/jborrow/scrunner
Author: Josh Borrow
Author-email: josh@joshborrow.com
License: UNKNOWN
Platform: UNKNOWN
Classifier: Programming Language :: Python :: 3.9
Classifier: Programming Language :: Python :: 3.10
Classifier: License :: OSI Approved :: MIT License
Classifier: Topic :: Utilities
Classifier: Operating System :: OS Independent
License-File: LICENSE
Requires-Dist: attrs (>=21.0.0)
Requires-Dist: jinja2 (>3.0.0)
